.gitignore
.gitmodules
.pylintrc
.readthedocs.yml
CODE_OF_CONDUCT.md
LICENSE
README.rst
requirements.txt
setup.py
.github/workflows/build.yml
.github/workflows/release.yml
docs/api.rst
docs/conf.py
docs/examples.rst
docs/index.rst
docs/_static/favicon.ico
examples/analog_in.py
examples/bbb_digitalio.py
examples/mcps_busio_i2c.py
examples/pb_digitalio.py
examples/pi_busio_i2c.py
examples/pi_busio_spi.py
examples/pi_digitalio.py
examples/piblinka.py
src/__version__.py
src/analogio.py
src/bitbangio.py
src/board.py
src/busio.py
src/digitalio.py
src/keypad.py
src/micropython.py
src/neopixel_write.py
src/pulseio.py
src/pwmio.py
src/rainbowio.py
src/adafruit_blinka/__init__.py
src/adafruit_blinka/agnostic/__init__.py
src/adafruit_blinka/agnostic/time.py
src/adafruit_blinka/board/__init__.py
src/adafruit_blinka/board/binho_nova.py
src/adafruit_blinka/board/clockworkcpi3.py
src/adafruit_blinka/board/coral_dev_board.py
src/adafruit_blinka/board/coral_dev_board_mini.py
src/adafruit_blinka/board/dragonboard_410c.py
src/adafruit_blinka/board/feather_huzzah.py
src/adafruit_blinka/board/feather_u2if.py
src/adafruit_blinka/board/ftdi_ft2232h.py
src/adafruit_blinka/board/ftdi_ft232h.py
src/adafruit_blinka/board/giantboard.py
src/adafruit_blinka/board/greatfet_one.py
src/adafruit_blinka/board/hifive_unleashed.py
src/adafruit_blinka/board/itsybitsy_u2if.py
src/adafruit_blinka/board/microchip_mcp2221.py
src/adafruit_blinka/board/nodemcu.py
src/adafruit_blinka/board/pico_u2if.py
src/adafruit_blinka/board/pine64.py
src/adafruit_blinka/board/pineH64.py
src/adafruit_blinka/board/pyboard.py
src/adafruit_blinka/board/qt2040_trinkey_u2if.py
src/adafruit_blinka/board/qtpy_u2if.py
src/adafruit_blinka/board/soPine.py
src/adafruit_blinka/board/tritium-h3.py
src/adafruit_blinka/board/udoo_x86ultra.py
src/adafruit_blinka/board/bananapi/__init__.py
src/adafruit_blinka/board/bananapi/bpim2zero.py
src/adafruit_blinka/board/beagleboard/__init__.py
src/adafruit_blinka/board/beagleboard/beaglebone_ai.py
src/samourai_Adafruit_Blinka.egg-info/PKG-INFO
src/samourai_Adafruit_Blinka.egg-info/SOURCES.txt
src/samourai_Adafruit_Blinka.egg-info/dependency_links.txt
src/samourai_Adafruit_Blinka.egg-info/requires.txt
src/samourai_Adafruit_Blinka.egg-info/top_level.txt
