Metadata-Version: 2.1
Name: samourai-Adafruit-Blinka
Version: 0.0.1a0
Summary: CircuitPython APIs for non-CircuitPython versions of Python such as CPython on Linux and MicroPython.
Home-page: https://github.com/adafruit/Adafruit_Blinka
Author: Adafruit Industries
Author-email: circuitpython@adafruit.com
License: MIT
Platform: UNKNOWN
Classifier: License :: OSI Approved :: MIT License
Classifier: Programming Language :: Python
Classifier: Programming Language :: Python :: 3
Classifier: Programming Language :: Python :: 3.6
Classifier: Programming Language :: Python :: Implementation :: MicroPython
Requires-Python: >=3.6.0
License-File: LICENSE
